ecv_aws_services/__init__.py
ecv_aws_services/aws_service.py
ecv_aws_services/cognito_service.py
ecv_aws_services/dynamodb_service.py
ecv_aws_services/eventbridge_service.py
ecv_aws_services/exceptions.py
ecv_aws_services/kms_service.py
ecv_aws_services/lambda_service.py
ecv_aws_services/py.typed
ecv_aws_services/s3_service.py
ecv_aws_services/secretsmanager_service.py
ecv_aws_services/ses_service.py
ecv_aws_services/sns_service.py
ecv_aws_services/sqs_service.py
ecv_aws_services/ssm_service.py
ecv_database/__init__.py
ecv_database/py.typed
ecv_helpers/__init__.py
ecv_helpers/py.typed
ecv_helpers/datetime/__init__.py
ecv_helpers/datetime/datetime.py
ecv_helpers/datetime/standard.py
ecv_helpers/debugger/__init__.py
ecv_helpers/debugger/debugging.py
ecv_helpers/files/__init__.py
ecv_helpers/files/file.py
ecv_helpers/formatter/__init__.py
ecv_helpers/formatter/formatter.py
ecv_helpers/formatter/regex.py
ecv_helpers/http/__init__.py
ecv_helpers/http/requests.py
ecv_helpers/http/response.py
ecv_helpers/logger/__init__.py
ecv_helpers/logger/logger.py
ecv_helpers/logger/metrics.py
ecv_helpers/logger/tracer.py
ecv_helpers/strings/__init__.py
ecv_helpers/strings/passwords.py
ecv_helpers/strings/uuid.py
ecv_serverless/__init__.py
ecv_serverless/py.typed
ecv_serverless/events/__init__.py
ecv_serverless/events/base.py
ecv_serverless/lambda_module/__init__.py
ecv_serverless/lambda_module/exceptions.py
ecv_serverless/lambda_module/handler.py
ecv_serverless/lambda_module/logger.py
ecv_serverless/lambda_module/metrics.py
ecv_serverless/lambda_module/response.py
ecv_serverless/lambda_module/tracer.py
ecv_serverless/lambda_module/validator.py
ecv_serverless/models/__init__.py
ecv_serverless/models/base.py
ecv_python_helpers-1.0.13.dist-info/LICENSE
ecv_python_helpers-1.0.13.dist-info/METADATA
ecv_python_helpers-1.0.13.dist-info/WHEEL
ecv_python_helpers-1.0.13.dist-info/top_level.txt
ecv_python_helpers-1.0.13.dist-info/RECORD
